ssl_rsa_secure/__init__.py
ssl_rsa_secure/rsaUtil.py
ssl_rsa_secure/sslUtil.py
ssl_rsa_secure-0.1.0.dist-info/METADATA
ssl_rsa_secure-0.1.0.dist-info/WHEEL
ssl_rsa_secure-0.1.0.dist-info/top_level.txt
ssl_rsa_secure-0.1.0.dist-info/RECORD
